umm/.DS_Store
umm/__init__.py
umm/cli/__init__.py
umm/cli/client.py
umm/cli/umm.py
umm/resources/commands.yaml
umm/resources/config.yaml
umm/server/__init__.py
umm/server/__main__.py
umm/server/command.py
umm/server/command_set.py
umm/server/routes.py
umm/server/utils.py
umm/utils/__init__.py
umm/utils/config.py
umm_cli_helper-1.0.0.dist-info/entry_points.txt
umm_cli_helper-1.0.0.dist-info/LICENSE
umm_cli_helper-1.0.0.dist-info/WHEEL
umm_cli_helper-1.0.0.dist-info/METADATA
umm_cli_helper-1.0.0.dist-info/RECORD
