Metadata-Version: 2.1
Name: umm-cli-helper
Version: 1.0.0
Summary: CLI tool for figuring out forgotten CLI commands through search and tagging
Home-page: https://github.com/zachcoleman/umm-cli-helper
License: MIT
Author: Zachary Coleman
Author-email: zacharywcoleman@gmail.com
Requires-Python: >=3.7,<4
Classifier: License :: OSI Approved :: MIT License
Classifier: Programming Language :: Python :: 3
Classifier: Programming Language :: Python :: 3.7
Classifier: Programming Language :: Python :: 3.8
Classifier: Programming Language :: Python :: 3.9
Requires-Dist: PyYAML (>=5.4.1,<6.0.0)
Requires-Dist: Pygments (>=2.10.0,<3.0.0)
Requires-Dist: aiohttp (>=3.7.4,<4.0.0)
Requires-Dist: click (>=8.0.1,<9.0.0)
Requires-Dist: pydantic (>=1.8.2,<2.0.0)
Requires-Dist: requests (>=2.26.0,<3.0.0)
Requires-Dist: setuptools (>=57.5.0,<58.0.0)
